MANIFEST.in
README.rst
requirements.txt
setup.py
log_to_kafka/__init__.py
log_to_kafka/default_settings.py
log_to_kafka/logger.py
log_to_kafka/settings_wrapper.py
log_to_kafka.egg-info/PKG-INFO
log_to_kafka.egg-info/SOURCES.txt
log_to_kafka.egg-info/dependency_links.txt
log_to_kafka.egg-info/requires.txt
log_to_kafka.egg-info/top_level.txt
log_to_kafka.egg-info/zip-safe
test/test_concurrent.py
test/test_lock.py
test/test_logger.py
test/test_stream.py