Metadata-Version: 1.1
Name: log-to-kafka
Version: 1.0.4
Summary: log to kafka
Home-page: https://www.github.com/ShichaoMa/log_to_kafka
Author: cn
Author-email: 308299269@qq.com
License: MIT
Keywords: log kafka
Platform: UNKNOWN
Classifier: License :: OSI Approved :: MIT License
Classifier: Programming Language :: Python
Classifier: Intended Audience :: Developers
Classifier: Operating System :: OS Independent
